pynik/__init__.py
pynik/libs/src/__init__.py
pynik/libs/src/github_helpers.py
pynik-0.1.3.dist-info/WHEEL
pynik-0.1.3.dist-info/METADATA
pynik-0.1.3.dist-info/RECORD
