Metadata-Version: 2.1
Name: pynik
Version: 0.1.3
Summary: This is a test project description
Author: Nik Sheridan
Author-email: nik.sheridan@gmail.com
Requires-Python: >=3.10,<4.0
Classifier: Programming Language :: Python :: 3
Classifier: Programming Language :: Python :: 3.10
Requires-Dist: loguru (>=0.6.0,<0.7.0)
